zpgs/__cls_aide_rst_base__.py
zpgs/__cls_aide_sql_pgs__.py
zpgs/__cls_pgs_conn__.py
zpgs/__init__.py
zpgs-3.0.dist-info/LICENSE
zpgs-3.0.dist-info/METADATA
zpgs-3.0.dist-info/WHEEL
zpgs-3.0.dist-info/top_level.txt
zpgs-3.0.dist-info/RECORD
