Metadata-Version: 2.1
Name: zpgs
Version: 3.0
Summary: A useless database connection based on psycopg2
Home-page: https://github.com/zzt/zpgs.git
Author: zhstack
Author-email: zhstack@163.com
License: MIT
Keywords: zpgs
License-File: LICENSE
Requires-Dist: psycopg2
